generativeai_for_python3.8-0.0.1-py3.8-nspkg.pth
google/generativeai/__init__.py
google/generativeai/answer.py
google/generativeai/caching.py
google/generativeai/client.py
google/generativeai/discuss.py
google/generativeai/embedding.py
google/generativeai/files.py
google/generativeai/generative_models.py
google/generativeai/models.py
google/generativeai/operations.py
google/generativeai/permission.py
google/generativeai/protos.py
google/generativeai/responder.py
google/generativeai/retriever.py
google/generativeai/string_utils.py
google/generativeai/text.py
google/generativeai/utils.py
google/generativeai/version.py
google/generativeai/notebook/__init__.py
google/generativeai/notebook/argument_parser.py
google/generativeai/notebook/cmd_line_parser.py
google/generativeai/notebook/command.py
google/generativeai/notebook/command_utils.py
google/generativeai/notebook/compare_cmd.py
google/generativeai/notebook/compile_cmd.py
google/generativeai/notebook/eval_cmd.py
google/generativeai/notebook/flag_def.py
google/generativeai/notebook/gspread_client.py
google/generativeai/notebook/html_utils.py
google/generativeai/notebook/input_utils.py
google/generativeai/notebook/ipython_env.py
google/generativeai/notebook/ipython_env_impl.py
google/generativeai/notebook/magics.py
google/generativeai/notebook/magics_engine.py
google/generativeai/notebook/model_registry.py
google/generativeai/notebook/output_utils.py
google/generativeai/notebook/parsed_args_lib.py
google/generativeai/notebook/post_process_utils.py
google/generativeai/notebook/post_process_utils_test_helper.py
google/generativeai/notebook/py_utils.py
google/generativeai/notebook/run_cmd.py
google/generativeai/notebook/sheets_id.py
google/generativeai/notebook/sheets_sanitize_url.py
google/generativeai/notebook/sheets_utils.py
google/generativeai/notebook/text_model.py
google/generativeai/notebook/lib/__init__.py
google/generativeai/notebook/lib/llm_function.py
google/generativeai/notebook/lib/llmfn_input_utils.py
generativeai_for_python3.8-0.0.1.dist-info/LICENSE
generativeai_for_python3.8-0.0.1.dist-info/METADATA
generativeai_for_python3.8-0.0.1.dist-info/WHEEL
generativeai_for_python3.8-0.0.1.dist-info/namespace_packages.txt
generativeai_for_python3.8-0.0.1.dist-info/top_level.txt
generativeai_for_python3.8-0.0.1.dist-info/RECORD
