Metadata-Version: 2.1
Name: generativeai-for-python3.8
Version: 0.0.1
Summary: for python3.8 generative google AI
Home-page: https://github.com/jstmn/generative-ai-python-3.8
Author: Google LLC
License: Apache 2.0
Platform: Posix; MacOS X; Windows
Classifier: Development Status :: 5 - Production/Stable
Classifier: Intended Audience :: Developers
Classifier: License :: OSI Approved :: Apache Software License
Classifier: Programming Language :: Python
Classifier: Programming Language :: Python :: 3
Classifier: Programming Language :: Python :: 3.9
Classifier: Programming Language :: Python :: 3.10
Classifier: Programming Language :: Python :: 3.11
Classifier: Programming Language :: Python :: 3.12
Classifier: Operating System :: OS Independent
Classifier: Topic :: Scientific/Engineering :: Artificial Intelligence
Requires-Python: >=3.8
Requires-Dist: google-ai-generativelanguage ==0.6.5
Requires-Dist: google-api-core
Requires-Dist: google-api-python-client
Requires-Dist: google-auth >=2.15.0
Requires-Dist: protobuf
Requires-Dist: pydantic
Requires-Dist: tqdm
Requires-Dist: typing-extensions
Provides-Extra: dev
Requires-Dist: absl-py ; extra == 'dev'
Requires-Dist: black ; extra == 'dev'
Requires-Dist: nose2 ; extra == 'dev'
Requires-Dist: pandas ; extra == 'dev'
Requires-Dist: pytype ; extra == 'dev'
Requires-Dist: pyyaml ; extra == 'dev'
Requires-Dist: Pillow ; extra == 'dev'
Requires-Dist: ipython ; extra == 'dev'
